jupyter_darkmodern/__init__.py
jupyter_darkmodern/_version.py
jupyter_darkmodern-0.1.0.data/data/share/jupyter/labextensions/jupyter_darkmodern/package.json
jupyter_darkmodern-0.1.0.data/data/share/jupyter/labextensions/jupyter_darkmodern/schemas/jupyter_darkmodern/package.json.orig
jupyter_darkmodern-0.1.0.data/data/share/jupyter/labextensions/jupyter_darkmodern/schemas/jupyter_darkmodern/plugin.json
jupyter_darkmodern-0.1.0.data/data/share/jupyter/labextensions/jupyter_darkmodern/static/509.e7ed76cc6303f61f401e.js
jupyter_darkmodern-0.1.0.data/data/share/jupyter/labextensions/jupyter_darkmodern/static/remoteEntry.ff8ff6e12e7a5b88dad9.js
jupyter_darkmodern-0.1.0.data/data/share/jupyter/labextensions/jupyter_darkmodern/static/style.js
jupyter_darkmodern-0.1.0.data/data/share/jupyter/labextensions/jupyter_darkmodern/static/third-party-licenses.json
jupyter_darkmodern-0.1.0.data/data/share/jupyter/labextensions/jupyter_darkmodern/themes/jupyter_darkmodern/index.css
jupyter_darkmodern-0.1.0.data/data/share/jupyter/labextensions/jupyter_darkmodern/themes/jupyter_darkmodern/index.js
jupyter_darkmodern-0.1.0.data/data/share/jupyter/labextensions/jupyter_darkmodern/install.json
jupyter_darkmodern-0.1.0.dist-info/METADATA
jupyter_darkmodern-0.1.0.dist-info/WHEEL
jupyter_darkmodern-0.1.0.dist-info/licenses/LICENSE
jupyter_darkmodern-0.1.0.dist-info/RECORD
