Metadata-Version: 2.4
Name: jupyter_darkmodern
Version: 0.1.0
Summary: A JupyterLab theme to visually match VSCode's Dark Modern theme.
Project-URL: Homepage, https://github.com/Philip-S-Martin/jupyter_darkmodern
Project-URL: Bug Tracker, https://github.com/Philip-S-Martin/jupyter_darkmodern/issues
Project-URL: Repository, https://github.com/Philip-S-Martin/jupyter_darkmodern.git
Author-email: Philip Martin <philipscottmartin01@gmail.com>
License: BSD 3-Clause License
License-File: LICENSE
Keywords: jupyter,jupyterlab,jupyterlab-extension
Classifier: Framework :: Jupyter
Classifier: Framework :: Jupyter :: JupyterLab
Classifier: Framework :: Jupyter :: JupyterLab :: 4
Classifier: Framework :: Jupyter :: JupyterLab :: Extensions
Classifier: Framework :: Jupyter :: JupyterLab :: Extensions :: Prebuilt
Classifier: Framework :: Jupyter :: JupyterLab :: Extensions :: Themes
Classifier: License :: OSI Approved :: BSD License
Classifier: Programming Language :: Python
Classifier: Programming Language :: Python :: 3
Classifier: Programming Language :: Python :: 3.9
Classifier: Programming Language :: Python :: 3.10
Classifier: Programming Language :: Python :: 3.11
Classifier: Programming Language :: Python :: 3.12
Classifier: Programming Language :: Python :: 3.13
Requires-Python: >=3.9
